{
  "paths": [
    "https://raw.githubusercontent.com/jr270504/jrpc29092025/refs/heads/main/jrmad_6.json",
    "https://raw.githubusercontent.com/jr270504/jrpc29092025/refs/heads/main/jrmad_5.json",
    "https://raw.githubusercontent.com/jr270504/jrpc29092025/refs/heads/main/jrmad_4.json",
    "https://raw.githubusercontent.com/jr270504/jrpc29092025/refs/heads/main/jrmad_3.json",
    "https://raw.githubusercontent.com/jr270504/jrpc29092025/refs/heads/main/jrmad_2.json",
    "https://raw.githubusercontent.com/jr270504/jrpc29092025/refs/heads/main/jrmad_1.json",
     "https://raw.githubusercontent.com/jr270504/jrpc29092025/refs/heads/main/jrmad_0.json"
    
  ],
  "values": {
    "dailyFreeCopies": 0,
    "adRewardCredits": 1,
    "adCooldownSeconds": 60,
    "maxRewardedAdsPerSession": 100,
    "maxInterstitialPerSession": 100,
    "interstitialCooldownSeconds": 30,
    "maxRewardedInterstitialPerSession": 100,
    "riCooldownSeconds": 30,
    "unlimitedCopyDurationSeconds": 300,
    "removeBannerDurationSeconds": 3600
  },
  "desiredOrder": [
      "Trending", "Retro", "Aesthetic", "Car","Cinematic", "Couple", "Birthday","Vintage", "Cultural", "Branding", "Sports", "Male", "Female"
    ],
  "festivals": {
  "USA": ["Thanksgiving", "Christmas", "Independence Day"],
  "India": ["Diwali", "Holi", "Eid"],
  "Japan": ["Hanami", "Obon", "New Year"],
    "Pakistan": ["Eid ul-Fitr", "Eid ul-Adha", "Independence Day", "Ramadan"],
},
  "keywords": ["ai", "prompt", "creative", "art", "design", "productivity"],
    "contentUrl": "https://play.google.com/store/apps/details?id=com.shaaddevstudio.picsprompt",
    "nonPersonalizedAds": false,
}
